bundled_script_processor/__init__.py
bundled_script_processor/bundled_script_processor.py
bundled_script_processor-0.4.0.dist-info/METADATA
bundled_script_processor-0.4.0.dist-info/WHEEL
bundled_script_processor-0.4.0.dist-info/licenses/LICENSE
bundled_script_processor-0.4.0.dist-info/RECORD
