Metadata-Version: 2.4
Name: bundled-script-processor
Version: 0.4.0
Summary: A SageMaker-compatible BundledScriptProcessor for running tar-bundled source dirs.
Project-URL: Homepage, https://github.com/maslick/bundled-script-processor
Project-URL: Source, https://github.com/maslick/bundled-script-processor
Project-URL: Issues, https://github.com/maslick/bundled-script-processor/issues
Author: Pavel Maslov
License-Expression: MIT
License-File: LICENSE
Requires-Python: >=3.10
Requires-Dist: sagemaker>=2.75.1
